algo_finaluri/__init__.py
algo_finaluri/ 15. დინამიკური პროგრამირება. (Parenthesization). (Edit Distance). (Knapsack problem)/58318-_1_.txt
algo_finaluri/ 15. დინამიკური პროგრამირება. (Parenthesization). (Edit Distance). (Knapsack problem)/__init__.py
algo_finaluri/ 15. დინამიკური პროგრამირება. (Parenthesization). (Edit Distance). (Knapsack problem)/editDistanceBU.py
algo_finaluri/ 15. დინამიკური პროგრამირება. (Parenthesization). (Edit Distance). (Knapsack problem)/editDistanceNaive.py
algo_finaluri/ 15. დინამიკური პროგრამირება. (Parenthesization). (Edit Distance). (Knapsack problem)/editDistanceTD.py
algo_finaluri/ 15. დინამიკური პროგრამირება. (Parenthesization). (Edit Distance). (Knapsack problem)/knapsackBU.py
algo_finaluri/ 15. დინამიკური პროგრამირება. (Parenthesization). (Edit Distance). (Knapsack problem)/knapsackRec.py
algo_finaluri/ 15. დინამიკური პროგრამირება. (Parenthesization). (Edit Distance). (Knapsack problem)/knapsackTD.py
algo_finaluri/ 15. დინამიკური პროგრამირება. (Parenthesization). (Edit Distance). (Knapsack problem)/optimalParenthesizationBU.py
algo_finaluri/ 15. დინამიკური პროგრამირება. (Parenthesization). (Edit Distance). (Knapsack problem)/optimalParenthesizationRec.py
algo_finaluri/ 15. დინამიკური პროგრამირება. (Parenthesization). (Edit Distance). (Knapsack problem)/optimalParenthesizationTD.py
algo_finaluri/ 16. ამოცანები რომლებიც იხსნება დინამიკური პროგრამირების საშუალებით./58416.txt
algo_finaluri/ 16. ამოცანები რომლებიც იხსნება დინამიკური პროგრამირების საშუალებით./__init__.py
algo_finaluri/ 16. ამოცანები რომლებიც იხსნება დინამიკური პროგრამირების საშუალებით./longestCommonSubsequenceBU.py
algo_finaluri/ 16. ამოცანები რომლებიც იხსნება დინამიკური პროგრამირების საშუალებით./longestCommonSubsequenceRec.py
algo_finaluri/ 16. ამოცანები რომლებიც იხსნება დინამიკური პროგრამირების საშუალებით./longestCommonSubsequenceTD.py
algo_finaluri/ 16. ამოცანები რომლებიც იხსნება დინამიკური პროგრამირების საშუალებით./longestPalindromicSubstringBU.py
algo_finaluri-0.1.1.dist-info/METADATA
algo_finaluri-0.1.1.dist-info/WHEEL
algo_finaluri-0.1.1.dist-info/top_level.txt
algo_finaluri-0.1.1.dist-info/RECORD
